{
    "format_version": 2,
    "tooth": "github.com/YoumiHa/Lip-Sese",
    "version": "0.0.3",
    "asset_url": "https://github.com/YoumiHa/Lip-Sese/archive/refs/tags/0.0.3.zip",
    "info": {
        "name": "SeTu",
        "description": "SESE",
        "author": "ALL LSP",
        "source": "github.com/YoumiHa/Lip-Sese",
        "tags": ["sese"]
    },
    "files": {
    "place": [
            {
                "src": "photo/*",
                "dest": "photo/"
            }
        ]
    }
}
